hpc_forge-0.1.0.dist-info/licenses/LICENSE
hpctools/__init__.py
hpctools/cli.py
hpctools/header.py
hpctools/makegen.py
hpctools/slurmgen.py
hpctools/utils.py
hpc_forge-0.1.0.dist-info/METADATA
hpc_forge-0.1.0.dist-info/WHEEL
hpc_forge-0.1.0.dist-info/entry_points.txt
hpc_forge-0.1.0.dist-info/top_level.txt
hpc_forge-0.1.0.dist-info/RECORD
