Metadata-Version: 2.4
Name: hpc-forge
Version: 0.1.0
Summary: A lightweight CLI toolkit for HPC automation (Makefiles, SLURM jobs, templates)
Home-page: https://github.com/diogocsilva12/hpctools
Author: Diogo Silva
Author-email: diogo.coelho.silva@gmail.com
License: MIT
Requires-Python: >=3.8
License-File: LICENSE
Requires-Dist: click
Requires-Dist: questionary
Requires-Dist: rich
Dynamic: author
Dynamic: author-email
Dynamic: home-page
Dynamic: license
Dynamic: license-file
Dynamic: requires-dist
Dynamic: requires-python
Dynamic: summary
